qc_lab/__init__.py
qc_lab/_build_hooks.py
qc_lab/_config.py
qc_lab/algorithm.py
qc_lab/constants.py
qc_lab/data.py
qc_lab/functions.py
qc_lab/ingredients.py
qc_lab/model.py
qc_lab/numerical_constants.py
qc_lab/simulation.py
qc_lab/utils.py
qc_lab/variable.py
qc_lab/algorithms/__init__.py
qc_lab/algorithms/fewest_switches_surface_hopping.py
qc_lab/algorithms/mean_field.py
qc_lab/dynamics/__init__.py
qc_lab/dynamics/dynamics.py
qc_lab/dynamics/parallel_driver_mpi.py
qc_lab/dynamics/parallel_driver_multiprocessing.py
qc_lab/dynamics/serial_driver.py
qc_lab/models/__init__.py
qc_lab/models/fmo_complex.py
qc_lab/models/holstein_lattice.py
qc_lab/models/spin_boson.py
qc_lab/models/tully_problem_one.py
qc_lab/models/tully_problem_three.py
qc_lab/models/tully_problem_two.py
qc_lab/tasks/__init__.py
qc_lab/tasks/collect_tasks.py
qc_lab/tasks/initialization_tasks.py
qc_lab/tasks/update_tasks.py
qc_lab-0.3.0a3.dist-info/LICENSE
qc_lab-0.3.0a3.dist-info/METADATA
qc_lab-0.3.0a3.dist-info/WHEEL
qc_lab-0.3.0a3.dist-info/top_level.txt
qc_lab-0.3.0a3.dist-info/RECORD
