Metadata-Version: 2.1
Name: qc_lab
Version: 0.3.0a3
Summary: QC Lab: a python package for quantum-classical modeling.
Author-email: Tempelaar Team <roel.tempelaar@northwestern.edu>
License: Apache License
Classifier: Development Status :: 3 - Alpha
Classifier: Intended Audience :: Education
Classifier: Programming Language :: Python :: 3
Classifier: Operating System :: MacOS :: MacOS X
Classifier: Operating System :: Microsoft :: Windows
Classifier: Operating System :: POSIX :: Linux
Classifier: License :: OSI Approved :: Apache Software License
Requires-Python: >=3.6
License-File: LICENSE
Requires-Dist: numpy
Requires-Dist: tqdm
Requires-Dist: h5py
Requires-Dist: matplotlib
Requires-Dist: numba
Provides-Extra: docs
Requires-Dist: sphinx; extra == "docs"
Requires-Dist: pydata-sphinx-theme; extra == "docs"
Requires-Dist: sphinx-design; extra == "docs"
Requires-Dist: sphinx-togglebutton; extra == "docs"
Requires-Dist: sphinxcontrib-mermaid; extra == "docs"
Requires-Dist: graphviz; extra == "docs"
Provides-Extra: tests
Requires-Dist: pytest; extra == "tests"
Requires-Dist: mpi4py; extra == "tests"
